lykkellemainisrael/__init__.py
lykkellemainisrael/healthcheckasia0.py
lykkellemainisrael/maincalculationprogeodasia0.py
lykkellemainisrael/mainmasterprogeodasia0.py
lykkellemainisrael-0.1.2.dist-info/LICENSE
lykkellemainisrael-0.1.2.dist-info/METADATA
lykkellemainisrael-0.1.2.dist-info/WHEEL
lykkellemainisrael-0.1.2.dist-info/top_level.txt
lykkellemainisrael-0.1.2.dist-info/RECORD
