Metadata-Version: 2.1
Name: lykkellemainisrael
Version: 0.1.2
Summary: Modules pertaining to lykkellemainisrael
Home-page: https://dev.azure.com/lykkelle/Lykkelle/_git/Lykkellescripts
Author: Lykkelle Inc
Author-email: admin@lykkelle.com
License: UNKNOWN
Platform: UNKNOWN
Classifier: Programming Language :: Python :: 3
Classifier: License :: OSI Approved :: MIT License
Classifier: Operating System :: OS Independent
Requires-Python: >=3.6
